odoo/addons/ddmrp_exclude_moves_adu_calc_sales/README.rst
odoo/addons/ddmrp_exclude_moves_adu_calc_sales/__init__.py
odoo/addons/ddmrp_exclude_moves_adu_calc_sales/__manifest__.py
odoo/addons/ddmrp_exclude_moves_adu_calc_sales/i18n/ddmrp_exclude_moves_adu_calc_sales.pot
odoo/addons/ddmrp_exclude_moves_adu_calc_sales/i18n/es.po
odoo/addons/ddmrp_exclude_moves_adu_calc_sales/i18n/it.po
odoo/addons/ddmrp_exclude_moves_adu_calc_sales/models/__init__.py
odoo/addons/ddmrp_exclude_moves_adu_calc_sales/models/sale_order_line.py
odoo/addons/ddmrp_exclude_moves_adu_calc_sales/readme/CONTRIBUTORS.md
odoo/addons/ddmrp_exclude_moves_adu_calc_sales/readme/DESCRIPTION.md
odoo/addons/ddmrp_exclude_moves_adu_calc_sales/static/description/icon.png
odoo/addons/ddmrp_exclude_moves_adu_calc_sales/static/description/index.html
odoo/addons/ddmrp_exclude_moves_adu_calc_sales/tests/__init__.py
odoo/addons/ddmrp_exclude_moves_adu_calc_sales/tests/test_ddmrp_exclude_moves_adu_calc_sales.py
odoo/addons/ddmrp_exclude_moves_adu_calc_sales/views/sale_order_view.xml
odoo_addon_ddmrp_exclude_moves_adu_calc_sales-18.0.2.0.0.1.dist-info/METADATA
odoo_addon_ddmrp_exclude_moves_adu_calc_sales-18.0.2.0.0.1.dist-info/WHEEL
odoo_addon_ddmrp_exclude_moves_adu_calc_sales-18.0.2.0.0.1.dist-info/top_level.txt
odoo_addon_ddmrp_exclude_moves_adu_calc_sales-18.0.2.0.0.1.dist-info/RECORD
